pyfootballdata/__init__.py
pyfootballdata/football_data.py
pyfootballdata/structs/__init__.py
pyfootballdata/structs/areas.py
pyfootballdata/structs/competitions.py
pyfootballdata/structs/entities_base.py
pyfootballdata/structs/entities_compound.py
pyfootballdata/structs/filters.py
pyfootballdata/structs/head2heads.py
pyfootballdata/structs/matches.py
pyfootballdata/structs/persons.py
pyfootballdata/structs/scorers.py
pyfootballdata/structs/seasons.py
pyfootballdata/structs/standings.py
pyfootballdata/structs/teams.py
pyfootballdata-0.0.4.dist-info/LICENSE
pyfootballdata-0.0.4.dist-info/METADATA
pyfootballdata-0.0.4.dist-info/WHEEL
pyfootballdata-0.0.4.dist-info/top_level.txt
pyfootballdata-0.0.4.dist-info/RECORD
