Metadata-Version: 2.1
Name: pyfootballdata
Version: 0.0.4
Summary: A companion client for the football-data.org API
Author-email: Serhii Kovalenko <cmajorsmith@gmail.com>
Project-URL: Homepage, https://github.com/cmajsmith/pyfootballdata
Project-URL: Issues, https://github.com/cmajsmith/pyfootballdata/issues
Classifier: Development Status :: 3 - Alpha
Classifier: Intended Audience :: Developers
Classifier: Intended Audience :: Education
Classifier: Intended Audience :: Science/Research
Classifier: License :: OSI Approved :: MIT License
Classifier: Natural Language :: English
Classifier: Operating System :: OS Independent
Classifier: Programming Language :: Python :: 3
Classifier: Programming Language :: Python :: 3.8
Classifier: Programming Language :: Python :: 3.9
Classifier: Programming Language :: Python :: 3.10
Classifier: Programming Language :: Python :: 3.11
Classifier: Programming Language :: Python :: 3.12
Classifier: Programming Language :: Python :: 3 :: Only
Classifier: Topic :: Software Development :: Libraries
Requires-Python: >=3.8
License-File: LICENSE
